koai/__init__.py
koai/benchmarks/__init__.py
koai/benchmarks/benchmarks.json
koai/benchmarks/evaluation.py
koai/benchmarks/finetune.py
koai/benchmarks/finetune_utils.py
koai/benchmarks/modeling_dp.py
koai/benchmarks/modeling_re.py
koai/benchmarks/postprocess.py
koai/benchmarks/preprocess.py
koai/benchmarks/trainer_qa.py
koai/benchmarks/utils_qa.py
koai/utils/__init__.py
koai/utils/iterable_dataset.py
koai/utils/rs_utils.cpython-38-darwin.so
koai/utils/text.py
koai-1.0.8.7.dist-info/METADATA
koai-1.0.8.7.dist-info/WHEEL
koai-1.0.8.7.dist-info/top_level.txt
koai-1.0.8.7.dist-info/RECORD
