Metadata-Version: 2.1
Name: koai
Version: 1.0.8.7
Summary: Korean AI Project
Home-page: https://github.com/hkjeon13/koai
Author: Eddie
Author-email: hkjeo13@gmail.com
License: MIT
Classifier: Intended Audience :: Developers
Classifier: Intended Audience :: Science/Research
Classifier: License :: OSI Approved :: MIT License
Classifier: Operating System :: OS Independent
Classifier: Programming Language :: Python :: 3
Requires-Python: >=3
Requires-Dist: transformers
Requires-Dist: datasets
Requires-Dist: seqeval
Requires-Dist: nltk
Requires-Dist: rouge-score
Requires-Dist: evaluate
Requires-Dist: sklearn
Requires-Dist: scipy
